setup.py
distributions_uda_ex/Binomialdistribution.py
distributions_uda_ex/Gaussiandistribution.py
distributions_uda_ex/Generaldistribution.py
distributions_uda_ex/__init__.py
distributions_uda_ex.egg-info/PKG-INFO
distributions_uda_ex.egg-info/SOURCES.txt
distributions_uda_ex.egg-info/dependency_links.txt
distributions_uda_ex.egg-info/not-zip-safe
distributions_uda_ex.egg-info/top_level.txt